rabbitmq_amqp_python_client/__init__.py
rabbitmq_amqp_python_client/address_helper.py
rabbitmq_amqp_python_client/amqp_consumer_handler.py
rabbitmq_amqp_python_client/asyncio/__init__.py
rabbitmq_amqp_python_client/asyncio/connection.py
rabbitmq_amqp_python_client/asyncio/consumer.py
rabbitmq_amqp_python_client/asyncio/environment.py
rabbitmq_amqp_python_client/asyncio/management.py
rabbitmq_amqp_python_client/asyncio/publisher.py
rabbitmq_amqp_python_client/common.py
rabbitmq_amqp_python_client/connection.py
rabbitmq_amqp_python_client/consumer.py
rabbitmq_amqp_python_client/delivery_context.py
rabbitmq_amqp_python_client/entities.py
rabbitmq_amqp_python_client/environment.py
rabbitmq_amqp_python_client/exceptions.py
rabbitmq_amqp_python_client/management.py
rabbitmq_amqp_python_client/options.py
rabbitmq_amqp_python_client/publisher.py
rabbitmq_amqp_python_client/py.typed
rabbitmq_amqp_python_client/qpid/proton/__init__.py
rabbitmq_amqp_python_client/qpid/proton/_common.py
rabbitmq_amqp_python_client/qpid/proton/_condition.py
rabbitmq_amqp_python_client/qpid/proton/_data.py
rabbitmq_amqp_python_client/qpid/proton/_delivery.py
rabbitmq_amqp_python_client/qpid/proton/_endpoints.py
rabbitmq_amqp_python_client/qpid/proton/_events.py
rabbitmq_amqp_python_client/qpid/proton/_exceptions.py
rabbitmq_amqp_python_client/qpid/proton/_handler.py
rabbitmq_amqp_python_client/qpid/proton/_handlers.py
rabbitmq_amqp_python_client/qpid/proton/_io.py
rabbitmq_amqp_python_client/qpid/proton/_message.py
rabbitmq_amqp_python_client/qpid/proton/_reactor.py
rabbitmq_amqp_python_client/qpid/proton/_selectable.py
rabbitmq_amqp_python_client/qpid/proton/_tracing.py
rabbitmq_amqp_python_client/qpid/proton/_transport.py
rabbitmq_amqp_python_client/qpid/proton/_url.py
rabbitmq_amqp_python_client/qpid/proton/_utils.py
rabbitmq_amqp_python_client/qpid/proton/_wrapper.py
rabbitmq_amqp_python_client/qpid/proton/handlers.py
rabbitmq_amqp_python_client/qpid/proton/py.typed
rabbitmq_amqp_python_client-0.4.1.dist-info/METADATA
rabbitmq_amqp_python_client-0.4.1.dist-info/WHEEL
rabbitmq_amqp_python_client-0.4.1.dist-info/licenses/LICENSE
rabbitmq_amqp_python_client-0.4.1.dist-info/RECORD
