Metadata-Version: 2.4
Name: rabbitmq-amqp-python-client
Version: 0.4.1
Summary: Python RabbitMQ client for AMQP 1.0 protocol
License: Apache-2.0 license
License-File: LICENSE
Author: RabbitMQ team
Requires-Python: >=3.9,<4.0
Classifier: License :: Other/Proprietary License
Classifier: Programming Language :: Python :: 3
Classifier: Programming Language :: Python :: 3.9
Classifier: Programming Language :: Python :: 3.10
Classifier: Programming Language :: Python :: 3.11
Classifier: Programming Language :: Python :: 3.12
Classifier: Programming Language :: Python :: 3.13
Classifier: Programming Language :: Python :: 3.14
Requires-Dist: packaging (>=23.0,<24.0)
Requires-Dist: python-qpid-proton (>=0.40.0,<0.41.0)
Requires-Dist: typing-extensions (>=4.13.0,<5.0.0)
